sales/__init__.py
sales/context_processors.py
sales/settings.py
sales/middleware/__init__.py
sales/middleware/sales.py
sales/templatetags/__init__.py
sales/templatetags/sales.py
src/sales/__init__.py
src/sales/context_processors.py
src/sales/settings.py
src/sales/middleware/__init__.py
src/sales/middleware/sales.py
src/sales/templatetags/__init__.py
src/sales/templatetags/sales.py
django_sales-0.1.3.dist-info/LICENSE.txt
django_sales-0.1.3.dist-info/METADATA
django_sales-0.1.3.dist-info/WHEEL
django_sales-0.1.3.dist-info/top_level.txt
django_sales-0.1.3.dist-info/RECORD
