Metadata-Version: 2.1
Name: django-sales
Version: 0.1.3
Summary: Display different contact details based on query parameter and cookie
Home-page: https://github.com/yifaneye/django-sales
Author: Yifan Ai
Author-email: yifanai@aol.com
License: UNKNOWN
Platform: UNKNOWN
Classifier: Programming Language :: Python :: 3
Classifier: License :: OSI Approved :: MIT License
Classifier: Operating System :: OS Independent
Requires-Dist: Django
